PyAnime/__init__.py
PyAnime4Up-1.9.dist-info/LICENSE
PyAnime4Up-1.9.dist-info/METADATA
PyAnime4Up-1.9.dist-info/WHEEL
PyAnime4Up-1.9.dist-info/top_level.txt
PyAnime4Up-1.9.dist-info/RECORD
