Metadata-Version: 2.1
Name: PyAnime4Up
Version: 1.9
Summary: A Selenium-less Python Anime4Up Library
Home-page: https://github.com/AmineSoukara/PyAnime4Up
Author: AmineSoukara
Author-email: AmineSoukara@gmail.com
License: MIT
Project-URL: Source, https://github.com/AmineSoukara/PyAnime4Up
Project-URL: Documentation, https://github.com/AmineSoukara/PyAnime4Up#readme
Project-URL: Tracker, https://github.com/AmineSoukara/PyAnime4Up/issues
Keywords: Anime Anime4Up Scrapper Python
Classifier: Development Status :: 5 - Production/Stable
Classifier: Intended Audience :: Developers
Classifier: Topic :: Software Development :: Build Tools
Classifier: Natural Language :: English
Classifier: License :: OSI Approved :: MIT License
Classifier: Operating System :: OS Independent
Classifier: Programming Language :: Python :: 3.6
Classifier: Programming Language :: Python :: 3.7
Classifier: Programming Language :: Python :: 3.8
Classifier: Programming Language :: Python :: 3.9
Classifier: Topic :: Internet
Requires-Python: >=3.6
License-File: LICENSE
Requires-Dist: aiohttp
Requires-Dist: urllib3
Requires-Dist: bs4
Requires-Dist: requests
